interpret_response/__init__.py
interpret_response/interpret_html_response.py
interpret_response/interpret_json_response.py
retrieve_response/__init__.py
retrieve_response/retrieve_response.py
datagrab-0.0.1.dist-info/METADATA
datagrab-0.0.1.dist-info/WHEEL
datagrab-0.0.1.dist-info/top_level.txt
datagrab-0.0.1.dist-info/RECORD
