Metadata-Version: 2.1
Name: datagrab
Version: 0.0.1
Summary: The easy way to access and interpret textual web resources
Home-page: https://github.com/HEtothe/datagrab
Author: HEtothe
License: MIT
Platform: UNKNOWN
Classifier: License :: OSI Approved :: MIT License
Classifier: Programming Language :: Python :: 3
Classifier: Programming Language :: Python :: 3.7
Requires-Dist: requests
